nbswitch-0.0.1.dist-info/METADATA
nbswitch-0.0.1.dist-info/WHEEL
nbswitch-0.0.1.dist-info/licenses/LICENSE
nbswitch/__init__.py
nbswitch/cli.py
nbswitch/core.py
nbswitch/server.py
nbswitch/utils.py
nbswitch-0.0.1.dist-info/RECORD
