Metadata-Version: 2.1
Name: nbswitch
Version: 0.0.1
Summary: NbSwitch is a tool for modifying the use case of lessons inside jupyter notebooks, pure markdown, and other file formats.
Author-Email: Ramon Perez <ramonpzg@protonmail.com>
License: Apache 2.0
Requires-Python: >=3.11
Requires-Dist: anthropic
Requires-Dist: instructor
Requires-Dist: bs4
Requires-Dist: fastapi
Requires-Dist: pydantic
Requires-Dist: nbconvert
Requires-Dist: nbformat
Requires-Dist: typer>=0.12.3
Requires-Dist: rich>=13.7.1
